botgen/__init__.py
botgen/adapters/__init__.py
botgen/adapters/web_adapter.py
botgen/bot_worker.py
botgen/conversation.py
botgen/conversation_state.py
botgen/core.py
botgen-0.0.2.dist-info/METADATA
botgen-0.0.2.dist-info/WHEEL
botgen-0.0.2.dist-info/RECORD
