Metadata-Version: 2.1
Name: botgen
Version: 0.0.2
Summary: Python based developer toolkit to build bots
Author: Joao Cabral
Author-email: jpfcabral@gmail.com
Requires-Python: >=3.10,<4.0
Classifier: Programming Language :: Python :: 3
Classifier: Programming Language :: Python :: 3.10
Classifier: Programming Language :: Python :: 3.11
Classifier: Programming Language :: Python :: 3.12
Requires-Dist: aiohttp (>=3.9.3,<4.0.0)
Requires-Dist: botbuilder-core (>=4.14.8,<5.0.0)
Requires-Dist: botbuilder-dialogs (>=4.14.8,<5.0.0)
Requires-Dist: loguru (>=0.7.2,<0.8.0)
